missingValues_python/missingValues.py
missingval_asharma_3027-1.0.dist-info/METADATA
missingval_asharma_3027-1.0.dist-info/WHEEL
missingval_asharma_3027-1.0.dist-info/entry_points.txt
missingval_asharma_3027-1.0.dist-info/top_level.txt
missingval_asharma_3027-1.0.dist-info/RECORD
