Metadata-Version: 2.1
Name: missingval-asharma-3027
Version: 1.0
Summary: A python package to handle Missing Values using SimpleImputer Class
Home-page: UNKNOWN
Author: Abhishek Sharma
Author-email: asharma1_be17@thapar.edu
License: UNKNOWN
Platform: UNKNOWN
Classifier: Programming Language :: Python :: 3
Classifier: License :: OSI Approved :: MIT License
Classifier: Operating System :: OS Independent
Requires-Python: >=3.6
Requires-Dist: requests
